{
  "uuid": "d3a1c29f-26ab-42b2-8354-fc0880334e6b",
  "objectType": "ONCE",
  "version": "0.2.0.0",
  "state": {
    "pid": 7450,
    "state": "running",
    "domain": "local.once",
    "host": "localhost",
    "ip": "127.0.0.1",
    "capabilities": [
      {
        "capability": "httpPort",
        "port": 42777
      },
      {
        "capability": "wsPort",
        "port": 42777
      }
    ],
    "isPrimaryServer": true,
    "uuid": "d3a1c29f-26ab-42b2-8354-fc0880334e6b",
    "platform": {
      "platform": "node",
      "version": "v24.5.0",
      "capabilities": [
        "server",
        "websocket",
        "p2p"
      ],
      "isOnline": true,
      "hostname": "localhost",
      "ip": "127.0.0.1"
    }
  },
  "metadata": {
    "created": "2025-08-30T21:47:28.158Z",
    "modified": "2025-08-30T21:47:28.158Z",
    "creator": "ONCE-v0.2.0.0",
    "description": "ONCE server Primary server instance",
    "tags": [
      "server",
      "once",
      "primary"
    ],
    "domain": "local.once",
    "host": "localhost",
    "port": 42777,
    "isPrimaryServer": true
  }
}